{
  "backend": "merged",
  "image_path": "/Users/delmedigo/Dev/FineTree/data/pdf_images/companies-reports_haigud_financial_report_2023_year_1/page_0006.png",
  "old_candidates": [
    {
      "bbox": [
        1263,
        475,
        71,
        34
      ],
      "score": 0.4725605249404907,
      "value": "71101",
      "confidence": 0.363431841135025,
      "source": "old"
    },
    {
      "bbox": [
        253,
        479,
        71,
        35
      ],
      "score": 0.5246543288230896,
      "value": "9,996",
      "confidence": 0.9651739597320557,
      "source": "old"
    },
    {
      "bbox": [
        600,
        479,
        21,
        28
      ],
      "score": 0.363442987203598,
      "value": "3",
      "confidence": 0.999634861946106,
      "source": "old"
    },
    {
      "bbox": [
        443,
        482,
        64,
        27
      ],
      "score": 0.5741457343101501,
      "value": "6,642",
      "confidence": 0.9431382417678833,
      "source": "old"
    },
    {
      "bbox": [
        486,
        518,
        23,
        25
      ],
      "score": 0.35498833656311035,
      "value": "3",
      "confidence": 0.9997420907020569,
      "source": "old"
    },
    {
      "bbox": [
        438,
        550,
        73,
        37
      ],
      "score": 0.48134374618530273,
      "value": "6,645",
      "confidence": 0.982205867767334,
      "source": "old"
    },
    {
      "bbox": [
        1226,
        655,
        64,
        37
      ],
      "score": 0.5013037323951721,
      "value": "7178",
      "confidence": 0.8212195038795471,
      "source": "old"
    },
    {
      "bbox": [
        273,
        658,
        48,
        29
      ],
      "score": 0.5039602518081665,
      "value": "745",
      "confidence": 0.9941486120223999,
      "source": "old"
    },
    {
      "bbox": [
        461,
        658,
        46,
        29
      ],
      "score": 0.4974175989627838,
      "value": "757",
      "confidence": 0.9977577328681946,
      "source": "old"
    },
    {
      "bbox": [
        600,
        660,
        21,
        25
      ],
      "score": 0.40231624245643616,
      "value": "4",
      "confidence": 0.9996457099914551,
      "source": "old"
    },
    {
      "bbox": [
        1146,
        687,
        78,
        35
      ],
      "score": 0.5302540063858032,
      "value": "1055",
      "confidence": 0.34715789556503296,
      "source": "old"
    },
    {
      "bbox": [
        440,
        692,
        69,
        36
      ],
      "score": 0.4524945914745331,
      "value": "1,103",
      "confidence": 0.9898151159286499,
      "source": "old"
    },
    {
      "bbox": [
        600,
        694,
        21,
        28
      ],
      "score": 0.40067678689956665,
      "value": "5",
      "confidence": 0.9703587889671326,
      "source": "old"
    },
    {
      "bbox": [
        257,
        696,
        62,
        30
      ],
      "score": 0.5670740008354187,
      "value": "1,065",
      "confidence": 0.9996011853218079,
      "source": "old"
    },
    {
      "bbox": [
        255,
        728,
        69,
        37
      ],
      "score": 0.47344884276390076,
      "value": "1,167",
      "confidence": 0.9982731342315674,
      "source": "old"
    },
    {
      "bbox": [
        443,
        731,
        66,
        32
      ],
      "score": 0.5206776857376099,
      "value": "1,055",
      "confidence": 0.9996645450592041,
      "source": "old"
    },
    {
      "bbox": [
        600,
        733,
        21,
        23
      ],
      "score": 0.37649980187416077,
      "value": "6",
      "confidence": 0.9889354109764099,
      "source": "old"
    },
    {
      "bbox": [
        438,
        765,
        73,
        37
      ],
      "score": 0.4693644046783447,
      "value": "2,915",
      "confidence": 0.9547720551490784,
      "source": "old"
    },
    {
      "bbox": [
        1240,
        834,
        57,
        36
      ],
      "score": 0.4710458815097809,
      "value": "103",
      "confidence": 0.36878231167793274,
      "source": "old"
    },
    {
      "bbox": [
        239,
        836,
        87,
        36
      ],
      "score": 0.458789199590683,
      "value": "10,904",
      "confidence": 0.9906434416770935,
      "source": "old"
    },
    {
      "bbox": [
        438,
        836,
        73,
        36
      ],
      "score": 0.4679940640926361,
      "value": "9,377",
      "confidence": 0.5030896663665771,
      "source": "old"
    },
    {
      "bbox": [
        598,
        836,
        23,
        30
      ],
      "score": 0.3757621943950653,
      "value": "7",
      "confidence": 0.9992687106132507,
      "source": "old"
    },
    {
      "bbox": [
        239,
        909,
        87,
        34
      ],
      "score": 0.555573582649231,
      "value": "23,877",
      "confidence": 0.9931614398956299,
      "source": "old"
    },
    {
      "bbox": [
        427,
        909,
        84,
        34
      ],
      "score": 0.5077016949653625,
      "value": "18,937",
      "confidence": 0.8887242078781128,
      "source": "old"
    },
    {
      "bbox": [
        287,
        1016,
        34,
        32
      ],
      "score": 0.4456475079059601,
      "value": "13",
      "confidence": 0.972831666469574,
      "source": "old"
    },
    {
      "bbox": [
        472,
        1016,
        37,
        30
      ],
      "score": 0.4547664225101471,
      "value": "10",
      "confidence": 0.9339187741279602,
      "source": "old"
    },
    {
      "bbox": [
        253,
        1051,
        73,
        36
      ],
      "score": 0.4968221187591553,
      "value": "9,435",
      "confidence": 0.7690930366516113,
      "source": "old"
    },
    {
      "bbox": [
        438,
        1051,
        73,
        34
      ],
      "score": 0.498562216758728,
      "value": "5,851",
      "confidence": 0.9798774123191833,
      "source": "old"
    },
    {
      "bbox": [
        600,
        1053,
        23,
        27
      ],
      "score": 0.34799352288246155,
      "value": "8",
      "confidence": 0.9967066645622253,
      "source": "old"
    },
    {
      "bbox": [
        251,
        1122,
        77,
        41
      ],
      "score": 0.42894846200942993,
      "value": "9,448",
      "confidence": 0.9910597205162048,
      "source": "old"
    },
    {
      "bbox": [
        438,
        1124,
        73,
        34
      ],
      "score": 0.478059858083725,
      "value": "5,861",
      "confidence": 0.9223409295082092,
      "source": "old"
    },
    {
      "bbox": [
        276,
        1192,
        57,
        39
      ],
      "score": 0.4951328933238983,
      "value": "(67)",
      "confidence": 0.928740918636322,
      "source": "old"
    },
    {
      "bbox": [
        948,
        1192,
        57,
        37
      ],
      "score": 0.47144150733947754,
      "value": "103",
      "confidence": 0.6778080463409424,
      "source": "old"
    },
    {
      "bbox": [
        600,
        1197,
        21,
        25
      ],
      "score": 0.40472766757011414,
      "value": "9",
      "confidence": 0.9991959929466248,
      "source": "old"
    },
    {
      "bbox": [
        1304,
        1263,
        55,
        37
      ],
      "score": 0.4656011462211609,
      "value": "103",
      "confidence": 0.679211437702179,
      "source": "old"
    },
    {
      "bbox": [
        1306,
        1339,
        48,
        27
      ],
      "score": 0.537979006767273,
      "value": "103",
      "confidence": 0.38062381744384766,
      "source": "old"
    },
    {
      "bbox": [
        276,
        1375,
        48,
        30
      ],
      "score": 0.502695620059967,
      "value": "735",
      "confidence": 0.9975346326828003,
      "source": "old"
    },
    {
      "bbox": [
        461,
        1375,
        48,
        30
      ],
      "score": 0.47964903712272644,
      "value": "670",
      "confidence": 0.9955850839614868,
      "source": "old"
    },
    {
      "bbox": [
        241,
        1409,
        83,
        35
      ],
      "score": 0.5571122169494629,
      "value": "10,904",
      "confidence": 0.5874337553977966,
      "source": "old"
    },
    {
      "bbox": [
        438,
        1409,
        71,
        35
      ],
      "score": 0.5271791815757751,
      "value": "9,377",
      "confidence": 0.9830893278121948,
      "source": "old"
    },
    {
      "bbox": [
        600,
        1409,
        21,
        28
      ],
      "score": 0.4314776062965393,
      "value": "7",
      "confidence": 0.9985799789428711,
      "source": "old"
    },
    {
      "bbox": [
        241,
        1446,
        83,
        34
      ],
      "score": 0.5183982849121094,
      "value": "11,639",
      "confidence": 0.8297061324119568,
      "source": "old"
    },
    {
      "bbox": [
        431,
        1448,
        78,
        28
      ],
      "score": 0.567656397819519,
      "value": "10,047",
      "confidence": 0.9961691498756409,
      "source": "old"
    },
    {
      "bbox": [
        589,
        1517,
        34,
        30
      ],
      "score": 0.4923273026943207,
      "value": "10",
      "confidence": 0.8213747143745422,
      "source": "old"
    },
    {
      "bbox": [
        895,
        1517,
        62,
        36
      ],
      "score": 0.5070300102233887,
      "value": "1918",
      "confidence": 0.7076219916343689,
      "source": "old"
    },
    {
      "bbox": [
        260,
        1519,
        61,
        30
      ],
      "score": 0.5288637280464172,
      "value": "1,690",
      "confidence": 0.9995837807655334,
      "source": "old"
    },
    {
      "bbox": [
        445,
        1519,
        62,
        30
      ],
      "score": 0.4957055449485779,
      "value": "1,967",
      "confidence": 0.9999313354492188,
      "source": "old"
    },
    {
      "bbox": [
        1306,
        1519,
        48,
        28
      ],
      "score": 0.5088642239570618,
      "value": "103",
      "confidence": 0.5431020855903625,
      "source": "old"
    },
    {
      "bbox": [
        1309,
        1590,
        45,
        27
      ],
      "score": 0.5031611323356628,
      "value": "103",
      "confidence": 0.7004632949829102,
      "source": "old"
    },
    {
      "bbox": [
        257,
        1592,
        67,
        28
      ],
      "score": 0.5518704652786255,
      "value": "1,167",
      "confidence": 0.980370044708252,
      "source": "old"
    },
    {
      "bbox": [
        445,
        1592,
        64,
        28
      ],
      "score": 0.572442352771759,
      "value": "1,055",
      "confidence": 0.9919148683547974,
      "source": "old"
    },
    {
      "bbox": [
        600,
        1592,
        23,
        25
      ],
      "score": 0.40517887473106384,
      "value": "6",
      "confidence": 0.9779671430587769,
      "source": "old"
    },
    {
      "bbox": [
        241,
        1624,
        87,
        37
      ],
      "score": 0.46246057748794556,
      "value": "14,496",
      "confidence": 0.9989888072013855,
      "source": "old"
    },
    {
      "bbox": [
        427,
        1624,
        84,
        37
      ],
      "score": 0.5092899203300476,
      "value": "13,069",
      "confidence": 0.9955720901489258,
      "source": "old"
    },
    {
      "bbox": [
        1238,
        1627,
        48,
        27
      ],
      "score": 0.5257262587547302,
      "value": "101",
      "confidence": 0.7040584683418274,
      "source": "old"
    },
    {
      "bbox": [
        241,
        1697,
        87,
        35
      ],
      "score": 0.5197252035140991,
      "value": "23,877",
      "confidence": 0.9807172417640686,
      "source": "old"
    },
    {
      "bbox": [
        429,
        1697,
        82,
        35
      ],
      "score": 0.5235517621040344,
      "value": "18,937",
      "confidence": 0.9959047436714172,
      "source": "old"
    }
  ],
  "fine_candidates": [
    {
      "bbox": [
        241,
        470,
        96,
        53
      ],
      "score": 0.5655941963195801,
      "value": "9,996",
      "confidence": 0.7448766827583313,
      "source": "fine_tuned"
    },
    {
      "bbox": [
        431,
        470,
        89,
        55
      ],
      "score": 0.5647149085998535,
      "value": "6,642",
      "confidence": 0.9515288472175598,
      "source": "fine_tuned"
    },
    {
      "bbox": [
        468,
        505,
        55,
        52
      ],
      "score": 0.4494539499282837,
      "value": "3",
      "confidence": 0.9965670108795166,
      "source": "fine_tuned"
    },
    {
      "bbox": [
        306,
        522,
        14,
        15
      ],
      "score": 0.45890167355537415,
      "value": "-",
      "confidence": 0.9562996625900269,
      "source": "fine_tuned"
    },
    {
      "bbox": [
        241,
        543,
        94,
        53
      ],
      "score": 0.5412065982818604,
      "value": "9,996",
      "confidence": 0.9029006361961365,
      "source": "fine_tuned"
    },
    {
      "bbox": [
        433,
        546,
        87,
        48
      ],
      "score": 0.60463547706604,
      "value": "6,645",
      "confidence": 0.6816297173500061,
      "source": "fine_tuned"
    },
    {
      "bbox": [
        445,
        644,
        78,
        59
      ],
      "score": 0.5230351090431213,
      "value": "757",
      "confidence": 0.9982234835624695,
      "source": "fine_tuned"
    },
    {
      "bbox": [
        262,
        646,
        75,
        57
      ],
      "score": 0.5372060537338257,
      "value": "745",
      "confidence": 0.8133623600006104,
      "source": "fine_tuned"
    },
    {
      "bbox": [
        600,
        662,
        21,
        23
      ],
      "score": 0.314124196767807,
      "value": "4",
      "confidence": 0.9976046085357666,
      "source": "fine_tuned"
    },
    {
      "bbox": [
        431,
        683,
        92,
        57
      ],
      "score": 0.5531718134880066,
      "value": "1,103",
      "confidence": 0.951850414276123,
      "source": "fine_tuned"
    },
    {
      "bbox": [
        246,
        687,
        87,
        48
      ],
      "score": 0.6024919748306274,
      "value": "1,065",
      "confidence": 0.7620890140533447,
      "source": "fine_tuned"
    },
    {
      "bbox": [
        431,
        719,
        89,
        55
      ],
      "score": 0.5833041071891785,
      "value": "1,055",
      "confidence": 0.5384712219238281,
      "source": "fine_tuned"
    },
    {
      "bbox": [
        248,
        724,
        85,
        48
      ],
      "score": 0.6029406785964966,
      "value": "1,167",
      "confidence": 0.9404276609420776,
      "source": "fine_tuned"
    },
    {
      "bbox": [
        429,
        758,
        96,
        55
      ],
      "score": 0.5508667826652527,
      "value": "2,915",
      "confidence": 0.497823029756546,
      "source": "fine_tuned"
    },
    {
      "bbox": [
        417,
        900,
        103,
        52
      ],
      "score": 0.586288571357727,
      "value": "18,937",
      "confidence": 0.9784672260284424,
      "source": "fine_tuned"
    },
    {
      "bbox": [
        235,
        904,
        100,
        46
      ],
      "score": 0.6038992404937744,
      "value": "23,877",
      "confidence": 0.9889183640480042,
      "source": "fine_tuned"
    },
    {
      "bbox": [
        278,
        1007,
        59,
        53
      ],
      "score": 0.49840280413627625,
      "value": "13",
      "confidence": 0.72682785987854,
      "source": "fine_tuned"
    },
    {
      "bbox": [
        463,
        1007,
        60,
        53
      ],
      "score": 0.49077972769737244,
      "value": "10",
      "confidence": 0.9454980492591858,
      "source": "fine_tuned"
    },
    {
      "bbox": [
        431,
        1042,
        94,
        52
      ],
      "score": 0.5584797859191895,
      "value": "5,851",
      "confidence": 0.9969891905784607,
      "source": "fine_tuned"
    },
    {
      "bbox": [
        246,
        1046,
        89,
        46
      ],
      "score": 0.5833564400672913,
      "value": "9,435",
      "confidence": 0.7561865448951721,
      "source": "fine_tuned"
    },
    {
      "bbox": [
        241,
        1115,
        96,
        52
      ],
      "score": 0.5530341863632202,
      "value": "9,448",
      "confidence": 0.7533811330795288,
      "source": "fine_tuned"
    },
    {
      "bbox": [
        429,
        1115,
        94,
        52
      ],
      "score": 0.568744421005249,
      "value": "5,861",
      "confidence": 0.5341144800186157,
      "source": "fine_tuned"
    },
    {
      "bbox": [
        269,
        1183,
        75,
        60
      ],
      "score": 0.5156125426292419,
      "value": "(67)",
      "confidence": 0.9769418835639954,
      "source": "fine_tuned"
    },
    {
      "bbox": [
        264,
        1366,
        71,
        50
      ],
      "score": 0.5342380404472351,
      "value": "735",
      "confidence": 0.995721697807312,
      "source": "fine_tuned"
    },
    {
      "bbox": [
        452,
        1366,
        66,
        53
      ],
      "score": 0.5348775386810303,
      "value": "670",
      "confidence": 0.9328094720840454,
      "source": "fine_tuned"
    },
    {
      "bbox": [
        431,
        1400,
        89,
        55
      ],
      "score": 0.5652164220809937,
      "value": "9,377",
      "confidence": 0.5347570776939392,
      "source": "fine_tuned"
    },
    {
      "bbox": [
        232,
        1403,
        105,
        52
      ],
      "score": 0.5559446215629578,
      "value": "10,904",
      "confidence": 0.7906337380409241,
      "source": "fine_tuned"
    },
    {
      "bbox": [
        420,
        1437,
        105,
        55
      ],
      "score": 0.5306844711303711,
      "value": "10,047",
      "confidence": 0.9471097588539124,
      "source": "fine_tuned"
    },
    {
      "bbox": [
        235,
        1439,
        105,
        53
      ],
      "score": 0.550382673740387,
      "value": "11,639",
      "confidence": 0.8566752672195435,
      "source": "fine_tuned"
    },
    {
      "bbox": [
        248,
        1508,
        89,
        55
      ],
      "score": 0.526796817779541,
      "value": "1,690",
      "confidence": 0.7975714802742004,
      "source": "fine_tuned"
    },
    {
      "bbox": [
        433,
        1508,
        90,
        55
      ],
      "score": 0.5493521690368652,
      "value": "1,967",
      "confidence": 0.6367413997650146,
      "source": "fine_tuned"
    },
    {
      "bbox": [
        251,
        1583,
        84,
        48
      ],
      "score": 0.590342104434967,
      "value": "1,167",
      "confidence": 0.9715978503227234,
      "source": "fine_tuned"
    },
    {
      "bbox": [
        436,
        1583,
        84,
        48
      ],
      "score": 0.6023939847946167,
      "value": "1,055",
      "confidence": 0.728286623954773,
      "source": "fine_tuned"
    },
    {
      "bbox": [
        235,
        1617,
        105,
        55
      ],
      "score": 0.5478968024253845,
      "value": "14,496",
      "confidence": 0.983272910118103,
      "source": "fine_tuned"
    },
    {
      "bbox": [
        420,
        1617,
        107,
        55
      ],
      "score": 0.5630247592926025,
      "value": "13,069",
      "confidence": 0.7302367687225342,
      "source": "fine_tuned"
    },
    {
      "bbox": [
        232,
        1688,
        105,
        53
      ],
      "score": 0.555749773979187,
      "value": "23,877",
      "confidence": 0.9784649610519409,
      "source": "fine_tuned"
    },
    {
      "bbox": [
        420,
        1688,
        105,
        53
      ],
      "score": 0.5648388266563416,
      "value": "18,937",
      "confidence": 0.7877411246299744,
      "source": "fine_tuned"
    },
    {
      "bbox": [
        788,
        2154,
        29,
        35
      ],
      "score": 0.37173575162887573,
      "value": "4",
      "confidence": 0.986224889755249,
      "source": "fine_tuned"
    }
  ],
  "merged_candidates": [
    {
      "bbox": [
        253,
        479,
        71,
        35
      ],
      "value": "9,996",
      "source": "matched"
    },
    {
      "bbox": [
        443,
        482,
        64,
        27
      ],
      "value": "6,642",
      "source": "matched"
    },
    {
      "bbox": [
        486,
        518,
        23,
        25
      ],
      "value": "3",
      "source": "matched"
    },
    {
      "bbox": [
        306,
        522,
        14,
        15
      ],
      "value": "-",
      "source": "fine_tuned"
    },
    {
      "bbox": [
        241,
        543,
        94,
        53
      ],
      "value": "9,996",
      "source": "fine_tuned"
    },
    {
      "bbox": [
        438,
        550,
        73,
        37
      ],
      "value": "6,645",
      "source": "matched"
    },
    {
      "bbox": [
        273,
        658,
        48,
        29
      ],
      "value": "745",
      "source": "matched"
    },
    {
      "bbox": [
        461,
        658,
        46,
        29
      ],
      "value": "757",
      "source": "matched"
    },
    {
      "bbox": [
        600,
        660,
        21,
        25
      ],
      "value": "4",
      "source": "matched"
    },
    {
      "bbox": [
        440,
        692,
        69,
        36
      ],
      "value": "1,103",
      "source": "matched"
    },
    {
      "bbox": [
        257,
        696,
        62,
        30
      ],
      "value": "1,065",
      "source": "matched"
    },
    {
      "bbox": [
        255,
        728,
        69,
        37
      ],
      "value": "1,167",
      "source": "matched"
    },
    {
      "bbox": [
        443,
        731,
        66,
        32
      ],
      "value": "1,055",
      "source": "matched"
    },
    {
      "bbox": [
        438,
        765,
        73,
        37
      ],
      "value": "2,915",
      "source": "matched"
    },
    {
      "bbox": [
        239,
        909,
        87,
        34
      ],
      "value": "23,877",
      "source": "matched"
    },
    {
      "bbox": [
        427,
        909,
        84,
        34
      ],
      "value": "18,937",
      "source": "matched"
    },
    {
      "bbox": [
        287,
        1016,
        34,
        32
      ],
      "value": "13",
      "source": "matched"
    },
    {
      "bbox": [
        472,
        1016,
        37,
        30
      ],
      "value": "10",
      "source": "matched"
    },
    {
      "bbox": [
        253,
        1051,
        73,
        36
      ],
      "value": "9,435",
      "source": "matched"
    },
    {
      "bbox": [
        438,
        1051,
        73,
        34
      ],
      "value": "5,851",
      "source": "matched"
    },
    {
      "bbox": [
        251,
        1122,
        77,
        41
      ],
      "value": "9,448",
      "source": "matched"
    },
    {
      "bbox": [
        438,
        1124,
        73,
        34
      ],
      "value": "5,861",
      "source": "matched"
    },
    {
      "bbox": [
        276,
        1192,
        57,
        39
      ],
      "value": "(67)",
      "source": "matched"
    },
    {
      "bbox": [
        276,
        1375,
        48,
        30
      ],
      "value": "735",
      "source": "matched"
    },
    {
      "bbox": [
        461,
        1375,
        48,
        30
      ],
      "value": "670",
      "source": "matched"
    },
    {
      "bbox": [
        241,
        1409,
        83,
        35
      ],
      "value": "10,904",
      "source": "matched"
    },
    {
      "bbox": [
        438,
        1409,
        71,
        35
      ],
      "value": "9,377",
      "source": "matched"
    },
    {
      "bbox": [
        241,
        1446,
        83,
        34
      ],
      "value": "11,639",
      "source": "matched"
    },
    {
      "bbox": [
        431,
        1448,
        78,
        28
      ],
      "value": "10,047",
      "source": "matched"
    },
    {
      "bbox": [
        260,
        1519,
        61,
        30
      ],
      "value": "1,690",
      "source": "matched"
    },
    {
      "bbox": [
        445,
        1519,
        62,
        30
      ],
      "value": "1,967",
      "source": "matched"
    },
    {
      "bbox": [
        257,
        1592,
        67,
        28
      ],
      "value": "1,167",
      "source": "matched"
    },
    {
      "bbox": [
        445,
        1592,
        64,
        28
      ],
      "value": "1,055",
      "source": "matched"
    },
    {
      "bbox": [
        241,
        1624,
        87,
        37
      ],
      "value": "14,496",
      "source": "matched"
    },
    {
      "bbox": [
        427,
        1624,
        84,
        37
      ],
      "value": "13,069",
      "source": "matched"
    },
    {
      "bbox": [
        241,
        1697,
        87,
        35
      ],
      "value": "23,877",
      "source": "matched"
    },
    {
      "bbox": [
        429,
        1697,
        82,
        35
      ],
      "value": "18,937",
      "source": "matched"
    },
    {
      "bbox": [
        788,
        2154,
        29,
        35
      ],
      "value": "4",
      "source": "fine_tuned"
    }
  ],
  "facts": [
    {
      "bbox": [
        253,
        479,
        71,
        35
      ],
      "value": "9,996"
    },
    {
      "bbox": [
        443,
        482,
        64,
        27
      ],
      "value": "6,642"
    },
    {
      "bbox": [
        486,
        518,
        23,
        25
      ],
      "value": "3"
    },
    {
      "bbox": [
        306,
        522,
        14,
        15
      ],
      "value": "-"
    },
    {
      "bbox": [
        241,
        543,
        94,
        53
      ],
      "value": "9,996"
    },
    {
      "bbox": [
        438,
        550,
        73,
        37
      ],
      "value": "6,645"
    },
    {
      "bbox": [
        273,
        658,
        48,
        29
      ],
      "value": "745"
    },
    {
      "bbox": [
        461,
        658,
        46,
        29
      ],
      "value": "757"
    },
    {
      "bbox": [
        600,
        660,
        21,
        25
      ],
      "value": "4"
    },
    {
      "bbox": [
        440,
        692,
        69,
        36
      ],
      "value": "1,103"
    },
    {
      "bbox": [
        257,
        696,
        62,
        30
      ],
      "value": "1,065"
    },
    {
      "bbox": [
        255,
        728,
        69,
        37
      ],
      "value": "1,167"
    },
    {
      "bbox": [
        443,
        731,
        66,
        32
      ],
      "value": "1,055"
    },
    {
      "bbox": [
        438,
        765,
        73,
        37
      ],
      "value": "2,915"
    },
    {
      "bbox": [
        239,
        909,
        87,
        34
      ],
      "value": "23,877"
    },
    {
      "bbox": [
        427,
        909,
        84,
        34
      ],
      "value": "18,937"
    },
    {
      "bbox": [
        287,
        1016,
        34,
        32
      ],
      "value": "13"
    },
    {
      "bbox": [
        472,
        1016,
        37,
        30
      ],
      "value": "10"
    },
    {
      "bbox": [
        253,
        1051,
        73,
        36
      ],
      "value": "9,435"
    },
    {
      "bbox": [
        438,
        1051,
        73,
        34
      ],
      "value": "5,851"
    },
    {
      "bbox": [
        251,
        1122,
        77,
        41
      ],
      "value": "9,448"
    },
    {
      "bbox": [
        438,
        1124,
        73,
        34
      ],
      "value": "5,861"
    },
    {
      "bbox": [
        276,
        1192,
        57,
        39
      ],
      "value": "(67)"
    },
    {
      "bbox": [
        276,
        1375,
        48,
        30
      ],
      "value": "735"
    },
    {
      "bbox": [
        461,
        1375,
        48,
        30
      ],
      "value": "670"
    },
    {
      "bbox": [
        241,
        1409,
        83,
        35
      ],
      "value": "10,904"
    },
    {
      "bbox": [
        438,
        1409,
        71,
        35
      ],
      "value": "9,377"
    },
    {
      "bbox": [
        241,
        1446,
        83,
        34
      ],
      "value": "11,639"
    },
    {
      "bbox": [
        431,
        1448,
        78,
        28
      ],
      "value": "10,047"
    },
    {
      "bbox": [
        260,
        1519,
        61,
        30
      ],
      "value": "1,690"
    },
    {
      "bbox": [
        445,
        1519,
        62,
        30
      ],
      "value": "1,967"
    },
    {
      "bbox": [
        257,
        1592,
        67,
        28
      ],
      "value": "1,167"
    },
    {
      "bbox": [
        445,
        1592,
        64,
        28
      ],
      "value": "1,055"
    },
    {
      "bbox": [
        241,
        1624,
        87,
        37
      ],
      "value": "14,496"
    },
    {
      "bbox": [
        427,
        1624,
        84,
        37
      ],
      "value": "13,069"
    },
    {
      "bbox": [
        241,
        1697,
        87,
        35
      ],
      "value": "23,877"
    },
    {
      "bbox": [
        429,
        1697,
        82,
        35
      ],
      "value": "18,937"
    },
    {
      "bbox": [
        788,
        2154,
        29,
        35
      ],
      "value": "4"
    }
  ]
}